space_agents/__init__.py
space_agents-0.0.1.dist-info/METADATA
space_agents-0.0.1.dist-info/WHEEL
space_agents-0.0.1.dist-info/RECORD
